adminlteui/__init__.py
adminlteui/admin.py
adminlteui/apps.py
adminlteui/core.py
adminlteui/filters.py
adminlteui/models.py
adminlteui/tests.py
adminlteui/views.py
adminlteui/widgets.py
adminlteui/__pycache__/__init__.cpython-39.pyc
adminlteui/locale/zh/LC_MESSAGES/django.mo
adminlteui/locale/zh/LC_MESSAGES/django.po
adminlteui/locale/zh_Hans/LC_MESSAGES/django.mo
adminlteui/locale/zh_Hans/LC_MESSAGES/django.po
adminlteui/migrations/__init__.py
adminlteui/static/admin/components/Ionicons/css/ionicons.css
adminlteui/static/admin/components/Ionicons/css/ionicons.min.css
adminlteui/static/admin/components/Ionicons/fonts/ionicons.eot
adminlteui/static/admin/components/Ionicons/fonts/ionicons.svg
adminlteui/static/admin/components/Ionicons/fonts/ionicons.ttf
adminlteui/static/admin/components/Ionicons/fonts/ionicons.woff
adminlteui/static/admin/components/bootstrap/dist/css/bootstrap-theme.css
adminlteui/static/admin/components/bootstrap/dist/css/bootstrap-theme.css.map
adminlteui/static/admin/components/bootstrap/dist/css/bootstrap-theme.min.css
adminlteui/static/admin/components/bootstrap/dist/css/bootstrap-theme.min.css.map
adminlteui/static/admin/components/bootstrap/dist/css/bootstrap.css
adminlteui/static/admin/components/bootstrap/dist/css/bootstrap.css.map
adminlteui/static/admin/components/bootstrap/dist/css/bootstrap.min.css
adminlteui/static/admin/components/bootstrap/dist/css/bootstrap.min.css.map
adminlteui/static/admin/components/bootstrap/dist/fonts/glyphicons-halflings-regular.eot
adminlteui/static/admin/components/bootstrap/dist/fonts/glyphicons-halflings-regular.svg
adminlteui/static/admin/components/bootstrap/dist/fonts/glyphicons-halflings-regular.ttf
adminlteui/static/admin/components/bootstrap/dist/fonts/glyphicons-halflings-regular.woff
adminlteui/static/admin/components/bootstrap/dist/fonts/glyphicons-halflings-regular.woff2
adminlteui/static/admin/components/bootstrap/dist/js/bootstrap.js
django_adminlte_ui-2.1.0.dist-info/LICENSE
django_adminlte_ui-2.1.0.dist-info/METADATA
django_adminlte_ui-2.1.0.dist-info/WHEEL
django_adminlte_ui-2.1.0.dist-info/top_level.txt
django_adminlte_ui-2.1.0.dist-info/RECORD
