Metadata-Version: 2.1
Name: django-adminlte-ui
Version: 2.1.0
Summary: django admin theme base on adminlte
Home-page: https://github.com/wuyue92tree/django-adminlte-ui
Author: wuyue
Author-email: wuyue92tree@163.com
Maintainer: wuyue
Maintainer-email: wuyue92tree@163.com
License: MIT
License-File: LICENSE
